setup.py
nose_bleed/__init__.py
nose_bleed/db.py
nose_bleed/diff.py
nose_bleed/plugin.py
nose_bleed.egg-info/PKG-INFO
nose_bleed.egg-info/SOURCES.txt
nose_bleed.egg-info/dependency_links.txt
nose_bleed.egg-info/entry_points.txt
nose_bleed.egg-info/not-zip-safe
nose_bleed.egg-info/requires.txt
nose_bleed.egg-info/top_level.txt