Metadata-Version: 1.0
Name: nose-bleed
Version: 0.5.1
Summary: A progressive coverage plugin for Nose.
Home-page: http://github.com/dcramer/nose-bleed
Author: David Cramer
Author-email: dcramer@gmail.com
License: Apache License 2.0
Platform: UNKNOWN
Classifier: Intended Audience :: Developers
Classifier: Intended Audience :: System Administrators
Classifier: Operating System :: OS Independent
Classifier: Topic :: Software Development
